.gitignore
.travis.yml
CHANGES.txt
CONTRIBUTORS.txt
README.txt
pavement.py
paver
requirements.txt
setup.py
tox.ini
example/app/__init__.py
src/rebecca/__init__.py
src/rebecca.sqla.egg-info/PKG-INFO
src/rebecca.sqla.egg-info/SOURCES.txt
src/rebecca.sqla.egg-info/dependency_links.txt
src/rebecca.sqla.egg-info/entry_points.txt
src/rebecca.sqla.egg-info/namespace_packages.txt
src/rebecca.sqla.egg-info/not-zip-safe
src/rebecca.sqla.egg-info/requires.txt
src/rebecca.sqla.egg-info/top_level.txt
src/rebecca/sqla/__init__.py
src/rebecca/sqla/components.py
src/rebecca/sqla/config.py
src/rebecca/sqla/interfaces.py
tests/test_components.py
tests/test_config.py