Metadata-Version: 1.1
Name: rebecca.sqla
Version: 0.1
Summary: pyramid context to load SQLAlchemy model.
Home-page: https://github.com/rebeccaframework/rebecca.sqla
Author: Atsushi Odagiri
Author-email: aodagx@gmail.com
License: MIT
Platform: UNKNOWN
Classifier: Framework :: Pyramid
Classifier: License :: OSI Approved :: MIT License
Classifier: Programming Language :: Python
Classifier: Programming Language :: Python :: 2.6
Classifier: Programming Language :: Python :: 2.7
Classifier: Programming Language :: Python :: 3
Classifier: Programming Language :: Python :: 3.2
Classifier: Programming Language :: Python :: 3.3
